cypherdataframe/__init__.py
cypherdataframe/branch_maker.py
cypherdataframe/config.py
cypherdataframe/cypher.py
cypherdataframe/testfunctions.py
cypherdataframe/garner_domain/BranchMaker.py
cypherdataframe/garner_domain/__init__.py
cypherdataframe/garner_domain/properties_defaults.py
cypherdataframe/garner_domain/logistics/TransferBranch.py
cypherdataframe/garner_domain/logistics/__init__.py
cypherdataframe/garner_domain/measure/MeasureBranch.py
cypherdataframe/garner_domain/measure/__init__.py
cypherdataframe/garner_domain/queries/AttachableTableQuery.py
cypherdataframe/garner_domain/queries/LogisticsTableQuery.py
cypherdataframe/garner_domain/queries/__init__.py
cypherdataframe/garner_domain/reference/ReferenceBranch.py
cypherdataframe/garner_domain/reference/__init__.py
cypherdataframe/garner_domain/status/AttainedArchivedBranch.py
cypherdataframe/garner_domain/status/AttainedBranch.py
cypherdataframe/garner_domain/status/ForecastedArchivedBranch.py
cypherdataframe/garner_domain/status/ForecastedBranch.py
cypherdataframe/garner_domain/status/__init__.py
cypherdataframe/model/Branch.py
cypherdataframe/model/Config.py
cypherdataframe/model/LabelNode.py
cypherdataframe/model/Property.py
cypherdataframe/model/Query.py
cypherdataframe/model/QueryAccumulation.py
cypherdataframe/model/__init__.py
cypherdataframe-0.11.3.dist-info/METADATA
cypherdataframe-0.11.3.dist-info/WHEEL
cypherdataframe-0.11.3.dist-info/top_level.txt
cypherdataframe-0.11.3.dist-info/RECORD
