Metadata-Version: 2.1
Name: cypherdataframe
Version: 0.11.3
Summary: Cypher Query to df Toolkit
Home-page: UNKNOWN
Author: Attila Vanderploeg
License: MIT
Platform: UNKNOWN
Requires-Dist: py2neo (>=2021.2.3)
Requires-Dist: dacite (>=1.6.0)
